PIL_DAT/__init__.py
PIL_DAT/_dat_arch.py
PIL_DAT/dat_2.py
PIL_DAT/dat_base.py
PIL_DAT/dat_light.py
PIL_DAT/dat_model.py
PIL_DAT/dat_s.py
PIL_DAT/Image.py
PIL_DAT/resources/__init__.py
PIL_DAT/resources/DAT_light_x2.pth
PIL_DAT/resources/DAT_light_x3.pth
PIL_DAT/resources/DAT_light_x4.pth
pillow_dat-0.1.11.dist-info/LICENSE
pillow_dat-0.1.11.dist-info/METADATA
pillow_dat-0.1.11.dist-info/WHEEL
pillow_dat-0.1.11.dist-info/RECORD
