Metadata-Version: 2.1
Name: pillow-dat
Version: 0.1.11
Summary: PIL × DAT - Pillow extension for AI-based image upscaling.
License: Apache-2.0
Author: LovinData
Author-email: ilovedata.jjia@gmail.com
Requires-Python: >=3.11,<4.0
Classifier: License :: OSI Approved :: Apache Software License
Classifier: Programming Language :: Python :: 3
Classifier: Programming Language :: Python :: 3.11
Classifier: Programming Language :: Python :: 3.12
Requires-Dist: einops (>=0.7.0,<0.8.0)
Requires-Dist: numpy (>=1.26.4,<2.0.0)
Requires-Dist: pillow (>=10.2.0,<11.0.0)
Requires-Dist: torch (>=2.2.1,<3.0.0)
